pycleora-2.0.0.dist-info/METADATA
pycleora-2.0.0.dist-info/WHEEL
pycleora-2.0.0.dist-info/licenses/LICENSE
pycleora/.gitignore
pycleora/__init__.py
pycleora/pycleora.cp38-win_amd64.pyd
pycleora-2.0.0.dist-info/RECORD
