Metadata-Version: 2.3
Name: pycleora
Version: 2.0.0
Classifier: Programming Language :: Rust
Classifier: Programming Language :: Python :: Implementation :: CPython
Classifier: Programming Language :: Python :: Implementation :: PyPy
License-File: LICENSE
License-File: LICENSE
Summary: Sparse hypergraph structure and markov-propagation for node embeddings embeddings exposed via Python bindings.
Home-Page: https://github.com/synerise/cleora
Author-email: Jacek Dabrowski <jack.dabrowski@synerise.com>
Requires-Python: >=3.7
Project-URL: Source Code, https://github.com/synerise/cleora
